{
    "intents": [
        {
            "tag": "onlineservicespassword",
            "patterns": [
                "i want to know about my online services password.",
                "i want to know about my online services password. how can i reset it?",
                "i want know to my tv password."
            ],
            "responses": [
                "okay sir. to reset your services password  go to www.worldlink.com.np click on \u201conline services\u201d (eservice.worldlink.com.np/login/) click on \u201cforgot password?\u201d (eservice.worldlink.com.np/recover/forgot_password) enter your username and email address/mobile number registered to the username.",
                "to reset your online services password to reset your services password go to www.worldlink.com.np click on \u201conline services\u201d (eservice.worldlink.com.np/login/) click on \u201cforgot password?\u201d (eservice.worldlink.com.np/recover/forgot_password) enter your username and email address/mobile number registered to the username."
            ],
            "context_set": ""
        }
    ]
}